{"pages_react_primary_share.md":"06af597d","pages_summary_qrcode.md":"d192b030","pages_summary_ts.md":"946a4c3d","pages_summary_weakmap.md":"05346dc3","pages_handwriting_promise.md":"018b3e21","pages_tschallenge_medium.md":"b4a23639","pages_summary_webpack_rollup.md":"76e6780a","pages_summary_storage.md":"6d1990fc","index.md":"a1094606","pages_about_2021.md":"f3f70433","pages_about_about.md":"df5e1c48","pages_algorithm_algorithm.md":"546bfc00","pages_algorithm_bitwise.md":"a7228343","pages_react_reactinterview_easy.md":"45c8cb18","pages_summary_v8.md":"5b8d1088","pages_tschallenge_easy.md":"b7582b77","pages_tschallenge_hard.md":"bb903bb2","pages_algorithm_greedy.md":"f971b573","pages_algorithm_link.md":"277ad42d","pages_algorithm_sort.md":"31d9e383","pages_algorithm_string.md":"dfbaa604","pages_chrome_render.md":"32289aef","pages_css_layout_flex.md":"9b9a423d","pages_css_layout_grid.md":"f5e7d6ed","pages_css_style_less.md":"c2419562","pages_handwriting_array.md":"a417bcfb","pages_handwriting_react.md":"b08f7e28","pages_handwriting_reg.md":"5bc6b36e","pages_interview_all_css_css.md":"8194bb3d","pages_interview_all_html.md":"e0ca3a78","pages_interview_all_js.md":"ee5300c1","pages_interview_heading_best2.md":"58812a1b","pages_interview_heading_best3.md":"f514e011","pages_interview_heading_route.md":"a6e43a7e","pages_network_application.md":"4b18c171","pages_network_cache.md":"293e14f0","pages_interview_heading_best1.md":"698f04d0","pages_network_http.md":"a7cfb8d5","pages_network_https.md":"024799d6","pages_algorithm_dynamic.md":"17bd0c57","pages_network_interview-network.md":"2b96964d","pages_network_overview.md":"a56f8218","pages_network_physics.md":"f4c35116","pages_network_statuscode.md":"52df59c1","pages_network_tcpudp.md":"d6b5281a","pages_network_transmission.md":"cab31aa0","pages_network_web.md":"e08d7f91","pages_network_websocket.md":"508342d5","pages_network_writing.md":"e8f3c9d4","pages_private_experience_2023.md":"36eac29d","pages_react_hard_commit_beforemutation.md":"a6e108ac","pages_react_hard_commit_commit.md":"60058bb1","pages_react_hard_commit_layout.md":"ecf9098e","pages_react_hard_commit_mutation.md":"2c503de5","pages_react_hard_commit_qa.md":"df57c9bb","pages_react_reactinterview_common.md":"9f73e482","pages_react_hard_constructure.md":"9ab48ed5","pages_react_hard_diff_arraydiff.md":"70721c2d","pages_react_hard_diff_diffpre.md":"400c86df","pages_react_hard_diff_singlediff.md":"f97f7112","pages_react_hard_fiberidea.md":"e8461c93","pages_react_hard_hooks_hooks.md":"d2ee2089","pages_react_hard_hooks_useid.md":"613d3043","pages_react_hard_hooks_usestate.md":"b22dade6","pages_react_hard_hooks_usecontext.md":"d96c5f1d","pages_react_hard_hooks_useeffect.md":"35a973ed","pages_react_hard_hooks_usereducer.md":"3e88b7fb","pages_react_hard_hooks_useref.md":"3dff04af","pages_react_hard_hooks_usetransition.md":"516e2528","pages_react_hard_readme.md":"afee496d","pages_react_hard_render_beginwork.md":"bf14ee51","pages_react_hard_render_completework.md":"788f5d69","pages_react_hard_scheduler_scheduler-origin.md":"4fd4e751","pages_react_hard_scheduler_scheduler.md":"505bc165","pages_react_hard_update_priority.md":"5d282cd4","pages_react_hard_update_update.md":"bfbc7801","pages_react_primary_cli.md":"92b54f0b","pages_react_primary_component.md":"f53f7701","pages_react_primary_diff.md":"783ccb50","pages_react_primary_github.md":"f33b6d09","pages_react_primary_hooks.md":"8554b05d","pages_react_primary_jsx.md":"be5cb9c0","pages_react_primary_lifecycle.md":"092bc967","pages_react_primary_more.md":"98c1809e","pages_react_primary_params.md":"3c9a0b1d","pages_react_primary_proxy.md":"b176a34f","pages_react_primary_pubsub.md":"f3d7006b","pages_react_primary_react-router.md":"268628e9","pages_react_hard_update_updatecode.md":"fc19c626","pages_react_primary_router.md":"30bdc9d9","pages_handwriting_handwriting.md":"d755f27f","pages_react_primary_todolist.md":"d08060af","pages_structure_readme.md":"638a5ceb","pages_structure_graph.md":"a654a91a","pages_structure_heap.md":"18ca20d9","pages_structure_link.md":"6f242f5a","pages_structure_map.md":"b135396d","pages_structure_queue.md":"2127867e","pages_structure_set.md":"70a16797","pages_structure_stack.md":"e7a5d452","pages_structure_start.md":"6a4e571a","pages_structure_tree.md":"c1056bb4","pages_summary_animate.md":"a18a29b2","pages_summary_engine.md":"ccdd8a22","pages_summary_event.md":"2879bc38","pages_summary_generator.md":"b8da526c","pages_summary_git.md":"57a36919","pages_summary_highf.md":"a9e0634d","pages_summary_inherit.md":"cae77713","pages_summary_iterator.md":"8cb08d44","pages_summary_jsrun.md":"7b172009","pages_summary_jsx2js.md":"3c4a87b1","pages_summary_login.md":"eedfbaf0","pages_summary_monorepo.md":"32feb783","pages_summary_npm.md":"fdbf326c","pages_react_hard_hooks_uselayouteffect.md":"0bc500b6","pages_summary_prototype.md":"d786e89b","pages_react_hard_writing.md":"5506ad99","pages_react_primary_antd.md":"94f954c2","pages_summary_arrayapi.md":"ca84cafd","pages_algorithm_tree.md":"29a3aa4f","pages_network_datalink.md":"8a2f8fd3","pages_react_hard_hooks_qa.md":"836aa189","pages_react_hard_hooks_usememo-callback.md":"c6d03998","pages_react_primary_react-redux.md":"5f8b236a","pages_react_primary_redux.md":"be05e2f6","pages_handwriting_part.md":"2cc0b6ea","pages_work_oneversion.md":"393f7cb4"}
