{"index.md":"b9a7323f","pages_about_2021.md":"fe6749a9","pages_about_about.md":"52466672","pages_css_layout_flex.md":"3e27b9cf","pages_css_layout_grid.md":"adddfccb","pages_interview_heading_best1.md":"be69f981","pages_interview_heading_best2.md":"d44da6e6","pages_interview_heading_best3.md":"7d8d99f0","pages_interview_heading_route.md":"1e0b3126","pages_network_application.md":"94057600","pages_network_datalink.md":"4df5d794","pages_network_overview.md":"de1ac8e8","pages_network_physics.md":"925293fd","pages_network_transmission.md":"d12f719f","pages_network_web.md":"5de4c131","pages_network_writing.md":"dc99191a","pages_react_hard_commit_beforemutation.md":"4f1d90b3","pages_react_hard_commit_commit.md":"e3ea8bec","pages_react_hard_commit_layout.md":"1f792e36","pages_react_hard_commit_mutation.md":"dab1a18f","pages_react_hard_commit_qa.md":"d2708da1","pages_react_hard_constructure.md":"ea5c39fe","pages_react_hard_diff_arraydiff.md":"af4026f0","pages_react_hard_diff_diffpre.md":"754d93e6","pages_react_hard_diff_singlediff.md":"9975c5f7","pages_react_hard_fiberidea.md":"c207b9a9","pages_react_hard_hooks_hooks.md":"5c1ca468","pages_react_hard_hooks_qa.md":"1a143737","pages_react_hard_hooks_useid.md":"940e9913","pages_react_hard_hooks_usestate.md":"127ad318","pages_react_hard_hooks_usecontext.md":"d6721b86","pages_react_hard_hooks_useeffect.md":"f2eec6cb","pages_react_hard_hooks_uselayouteffect.md":"78f5f85e","pages_react_hard_hooks_usememo-callback.md":"74b769e5","pages_react_hard_hooks_usereducer.md":"15387043","pages_react_hard_hooks_useref.md":"eb8439e6","pages_react_hard_hooks_usetransition.md":"9021288f","pages_react_hard_readme.md":"217fc0b7","pages_react_hard_render_beginwork.md":"b90bd9db","pages_react_hard_render_completework.md":"fa72b82d","pages_react_hard_scheduler_scheduler-origin.md":"130cce87","pages_react_hard_scheduler_scheduler.md":"e6c9b8db","pages_react_hard_update_priority.md":"9022149a","pages_react_hard_update_update.md":"955e9f67","pages_react_hard_update_updatecode.md":"d6c4901a","pages_react_hard_writing.md":"f41546a0","pages_react_primary_antd.md":"e2b0e09a","pages_react_primary_cli.md":"d59f5feb","pages_react_primary_component.md":"bd54e8d2","pages_react_primary_diff.md":"a367f10d","pages_react_primary_github.md":"1444560e","pages_react_primary_hooks.md":"3b8fede6","pages_react_primary_jsx.md":"ff0060c0","pages_react_primary_lifecycle.md":"ebc12e71","pages_react_primary_more.md":"a0e23acd","pages_react_primary_params.md":"31b9e558","pages_react_primary_proxy.md":"b16145f3","pages_react_primary_pubsub.md":"539679da","pages_react_primary_react-redux.md":"eb8ab030","pages_react_primary_react-router.md":"3fe202f2","pages_react_primary_redux.md":"0a3bec77","pages_react_primary_router.md":"06d307f5","pages_react_primary_share.md":"ae7c8321","pages_react_primary_todolist.md":"bb899d99","pages_structure_readme.md":"36b81805","pages_structure_graph.md":"c58e08d4","pages_structure_heap.md":"e06f63db","pages_structure_link.md":"b4ab5909","pages_structure_map.md":"3814e981","pages_structure_queue.md":"7d47827c","pages_structure_set.md":"8e198449","pages_structure_stack.md":"143fa500","pages_structure_start.md":"649a905c","pages_structure_tree.md":"92561342","pages_summary_animate.md":"ce27c480","pages_summary_arrayapi.md":"52995e42","pages_summary_event.md":"f296e8eb","pages_summary_generator.md":"58686557","pages_summary_git.md":"b6b77404","pages_summary_highf.md":"d80ed4bd","pages_summary_inherit.md":"79c3e995","pages_summary_iterator.md":"f0b599d2","pages_summary_jsrun.md":"f5fd2b88","pages_summary_npm.md":"eace44b8","pages_summary_prototype.md":"a813617c","pages_summary_qrcode.md":"d3be41a5","pages_summary_storage.md":"eb4d5158","pages_summary_ts.md":"e8774e49","pages_summary_v8.md":"0b762746","pages_summary_weakmap.md":"13c2afce","pages_tschallenge_easy.md":"94b4c834","pages_tschallenge_hard.md":"b0f68f5c","pages_tschallenge_medium.md":"9a2af32d"}
