{"pages_about_2021.md":"1f5fd33f","index.md":"4942c55b","pages_about_about.md":"a6474bbc","pages_algorithm_algorithm.md":"48d9b5e9","pages_algorithm_bitwise.md":"3042705b","pages_algorithm_greedy.md":"a89a1599","pages_algorithm_link.md":"acf3beb5","pages_algorithm_sort.md":"0680b6cb","pages_algorithm_tree.md":"d19e0fc4","pages_chrome_render.md":"4432c8ea","pages_css_style_less.md":"cd166065","pages_react_hard_commit_qa.md":"417a8011","pages_react_hard_constructure.md":"09695261","pages_css_layout_flex.md":"d4be1bd5","pages_react_hard_diff_arraydiff.md":"205e49a4","pages_react_hard_diff_diffpre.md":"c26a2d57","pages_react_hard_diff_singlediff.md":"3ccdcadd","pages_react_hard_hooks_hooks.md":"5ff4505d","pages_react_primary_diff.md":"dc2c5ca7","pages_react_hard_fiberidea.md":"51d6a725","pages_react_primary_github.md":"07b5793f","pages_react_hard_hooks_qa.md":"d57590c7","pages_react_primary_hooks.md":"cbfee3fa","pages_react_primary_jsx.md":"02e496e8","pages_react_primary_lifecycle.md":"8eb53e9f","pages_react_hard_hooks_useid.md":"cb72e42c","pages_react_primary_more.md":"b5d48a80","pages_react_primary_params.md":"f03b3fe1","pages_react_primary_proxy.md":"a5b8b5e6","pages_react_primary_pubsub.md":"a0306e7a","pages_react_primary_react-redux.md":"0fafdd4f","pages_react_hard_hooks_usecontext.md":"6aa11263","pages_react_hard_hooks_usestate.md":"8f6b0347","pages_react_primary_router.md":"a5756d5f","pages_react_primary_share.md":"0b0e2e24","pages_react_reactinterview_common.md":"e6c381cf","pages_structure_readme.md":"baeea9a7","pages_react_primary_react-router.md":"f85fd2f2","pages_handwriting_handwriting.md":"b387a3da","pages_react_hard_hooks_useeffect.md":"83f35f53","pages_react_hard_hooks_uselayouteffect.md":"6547bb1a","pages_react_hard_readme.md":"085c817a","pages_react_hard_hooks_usereducer.md":"994c166e","pages_react_hard_hooks_usememo-callback.md":"c13c0e4c","pages_react_hard_hooks_useref.md":"07fd355f","pages_react_hard_hooks_usetransition.md":"4cef4d38","pages_react_hard_update_updatecode.md":"1e1d4491","pages_react_hard_update_update.md":"ff651f29","pages_react_hard_render_completework.md":"5a63fd36","pages_react_hard_scheduler_scheduler-origin.md":"ea0b9c0f","pages_react_hard_update_priority.md":"664e5ea3","pages_react_primary_cli.md":"04b1b6d5","pages_react_primary_antd.md":"c81eb9e2","pages_react_hard_scheduler_scheduler.md":"cd9c7aa9","pages_handwriting_react.md":"98698120","pages_handwriting_reg.md":"10c996e0","pages_interview_all_html.md":"b7bc0198","pages_interview_heading_best1.md":"b4c44247","pages_interview_heading_best3.md":"4e3360ba","pages_interview_heading_route.md":"4565099b","pages_network_application.md":"32ee6376","pages_react_primary_component.md":"37006845","pages_interview_all_css_css.md":"02860b31","pages_interview_all_js.md":"55bea9e5","pages_interview_heading_best2.md":"62d71855","pages_network_cache.md":"c0094e92","pages_network_datalink.md":"2941a3c7","pages_network_http.md":"60252b87","pages_network_overview.md":"ed1b417b","pages_network_https.md":"52e1bc67","pages_network_interview-network.md":"42981b9b","pages_structure_heap.md":"8c120cae","pages_structure_link.md":"43b6cfb5","pages_structure_map.md":"1143ca3a","pages_structure_set.md":"9c33537a","pages_structure_queue.md":"5778141d","pages_structure_start.md":"48b51005","pages_structure_stack.md":"239d590b","pages_structure_tree.md":"0bf35496","pages_summary_animate.md":"7b0b5422","pages_summary_arrayapi.md":"f2aebaf9","pages_summary_event.md":"49ba1c1b","pages_summary_git.md":"a101939f","pages_summary_highf.md":"d5ed9a6a","pages_summary_inherit.md":"43742b51","pages_summary_jsrun.md":"73a6e800","pages_summary_iterator.md":"ba51d601","pages_summary_engine.md":"a6b18a73","pages_summary_login.md":"3e670442","pages_summary_generator.md":"9560a53f","pages_react_primary_redux.md":"778aadc6","pages_network_tcpudp.md":"7e9c5c0d","pages_network_transmission.md":"81d4ef72","pages_network_web.md":"b2051c94","pages_network_websocket.md":"ba34c676","pages_network_writing.md":"65fffc4f","pages_private_experience_2023.md":"2d7b4298","pages_summary_npm.md":"8e3f5f33","pages_summary_qrcode.md":"b3cec154","pages_summary_ts.md":"31ceccf5","pages_react_hard_commit_beforemutation.md":"fb39c69e","pages_react_hard_commit_commit.md":"05c95381","pages_summary_storage.md":"555c62e4","pages_summary_v8.md":"0dc26040","pages_summary_weakmap.md":"8ef86092","pages_react_hard_commit_layout.md":"974c7ace","pages_tschallenge_easy.md":"f971f326","pages_network_physics.md":"f59866ec","pages_tschallenge_hard.md":"8d4395de","pages_react_hard_commit_mutation.md":"951a1469","pages_react_primary_todolist.md":"b7b5627e","pages_algorithm_dynamic.md":"5d1a3d4c","pages_css_layout_grid.md":"43c8ea88","pages_handwriting_array.md":"eae65489","pages_algorithm_string.md":"497b774e","pages_structure_graph.md":"8d2a749d","pages_summary_jsx2js.md":"7750579c","pages_react_hard_writing.md":"db3d1e45","pages_handwriting_part.md":"274693ba","pages_handwriting_promise.md":"4298d16e","pages_react_hard_render_beginwork.md":"3288881e","pages_summary_prototype.md":"b1985f92","pages_network_statuscode.md":"7ebf9d9b","pages_tschallenge_medium.md":"3b7bf74e"}
